cynetdiff-0.1.18.dist-info/RECORD
cynetdiff-0.1.18.dist-info/WHEEL
cynetdiff-0.1.18.dist-info/METADATA
cynetdiff-0.1.18.dist-info/licenses/LICENSE
cynetdiff/models.pyx
cynetdiff/__init__.py
cynetdiff/utils.py
cynetdiff/models.pyi
cynetdiff/py.typed
cynetdiff/models.pxd
cynetdiff/models.cpython-310-darwin.so
