Metadata-Version: 2.4
Name: cynetdiff
Version: 0.1.18
Summary: A fast network diffusion library
Author-Email: "Eliot W. Robson" <eliot.robson24@gmail.com>
Maintainer-Email: "Eliot W. Robson" <eliot.robson24@gmail.com>, "Abhishek K. Umrawal" <aumrawal@illinois.edu>
License-Expression: MIT
License-File: LICENSE
Classifier: Development Status :: 3 - Alpha
Classifier: Programming Language :: Python :: 3.10
Classifier: Programming Language :: Python :: 3.11
Classifier: Programming Language :: Python :: 3.12
Classifier: Programming Language :: Python :: 3.13
Classifier: Topic :: Scientific/Engineering :: Mathematics
Classifier: Intended Audience :: Science/Research
Project-URL: homepage, https://github.com/eliotwrobson/CyNetDiff
Project-URL: tracker, https://github.com/eliotwrobson/CyNetDiff/issues
Project-URL: documentation, https://eliotwrobson.github.io/CyNetDiff/
Requires-Python: >=3.10
